colortest/__init__.py
colortest/__main__.py
colortest/_cli.py
colortest/tests/__init__.py
colortest-0.2.3.dist-info/COPYING
colortest-0.2.3.dist-info/METADATA
colortest-0.2.3.dist-info/WHEEL
colortest-0.2.3.dist-info/entry_points.txt
colortest-0.2.3.dist-info/top_level.txt
colortest-0.2.3.dist-info/RECORD
